LICENCE
MANIFEST.in
README.md
setup.py
code/png/PngImagePlugin.py
code/png/__init__.py
code/png/png.py
code/png/pngfilters.c
code/png/pngfilters.pxd
man/ca.rst
man/chunk.rst
man/conf.py
man/cython.rst
man/ex.rst
man/index.rst
man/png.rst
man/roadmap.rst
purepng.egg-info/PKG-INFO
purepng.egg-info/SOURCES.txt
purepng.egg-info/dependency_links.txt
purepng.egg-info/top_level.txt